alu/src/alu_top.v
module alu_top (
    input        clk,
    input        rst,
    input  [3:0] a,
    input  [3:0] b,
    input  [2:0] sel,
    output reg [4:0] result
);

always @(posedge clk) begin
    if (rst)
        result <= 5'b0;
    else begin
        case(sel)
            3'b000: result <= a + b;
            3'b001: result <= a - b;
            3'b010: result <= a & b;
            3'b011: result <= a | b;
            3'b100: result <= a ^ b;
            3'b101: result <= ~(a & b);
            3'b110: result <= a << 1;
            3'b111: result <= a >> 1;
        endcase
    end
end

endmodule

tb_alu_top.v
`timescale 1ns/1ps

module tb_alu_top;

reg clk;
reg rst;
reg [3:0] a;
reg [3:0] b;
reg [2:0] sel;
wire [4:0] result;

// Instantiate DUT
alu_top uut (
    .clk(clk),
    .rst(rst),
    .a(a),
    .b(b),
    .sel(sel),
    .result(result)
);

// Clock generation: 10 ns period (100 MHz)
always #5 clk = ~clk;

initial begin
    // Dump waveform
    $dumpfile("alu_top.vcd");
    $dumpvars(0, tb_alu_top);

    // Initialize
    clk = 0;
    rst = 1;
    a = 0;
    b = 0;
    sel = 0;

    // Apply reset
    #20;
    rst = 0;

    // Test Addition
    a = 4'd5; b = 4'd3; sel = 3'b000;
    #10;

    // Test Subtraction
    a = 4'd9; b = 4'd4; sel = 3'b001;
    #10;

    // Test AND
    a = 4'b1100; b = 4'b1010; sel = 3'b010;
    #10;

    // Test OR
    a = 4'b1100; b = 4'b1010; sel = 3'b011;
    #10;

    // Test XOR
    a = 4'b1100; b = 4'b1010; sel = 3'b100;
    #10;

    // Test NAND
    a = 4'b1100; b = 4'b1010; sel = 3'b101;
    #10;

    // Test Left Shift
    a = 4'b0011; sel = 3'b110;
    #10;

    // Test Right Shift
    a = 4'b1100; sel = 3'b111;
    #10;

    #20;
    $finish;
end

initial begin
    $monitor("Time=%0t clk=%b rst=%b sel=%b a=%d b=%d result=%d",
             $time, clk, rst, sel, a, b, result);
end

endmodule

alu/alu_top.vcd
$date
	Tue Jun 16 16:05:41 2026
$end
$version
	Icarus Verilog
$end
$timescale
	1ps
$end
$scope module tb_alu_top $end
$var wire 5 ! result [4:0] $end
$var reg 4 " a [3:0] $end
$var reg 4 # b [3:0] $end
$var reg 1 $ clk $end
$var reg 1 % rst $end
$var reg 3 & sel [2:0] $end
$scope module uut $end
$var wire 4 ' a [3:0] $end
$var wire 4 ( b [3:0] $end
$var wire 1 $ clk $end
$var wire 1 % rst $end
$var wire 3 ) sel [2:0] $end
$var reg 5 * result [4:0] $end
$upscope $end
$upscope $end
$enddefinitions $end
#0
$dumpvars
bx *
b0 )
b0 (
b0 '
b0 &
1%
0$
b0 #
b0 "
bx !
$end
#5000
b0 !
b0 *
1$
#10000
0$
#15000
1$
#20000
0$
b11 #
b11 (
b101 "
b101 '
0%
#25000
b1000 !
b1000 *
1$
#30000
0$
b1 &
b1 )
b100 #
b100 (
b1001 "
b1001 '
#35000
b101 !
b101 *
1$
#40000
0$
b10 &
b10 )
b1010 #
b1010 (
b1100 "
b1100 '
#45000
b1000 !
b1000 *
1$
#50000
0$
b11 &
b11 )
#55000
b1110 !
b1110 *
1$
#60000
0$
b100 &
b100 )
#65000
b110 !
b110 *
1$
#70000
0$
b101 &
b101 )
#75000
b10111 !
b10111 *
1$
#80000
0$
b110 &
b110 )
b11 "
b11 '
#85000
b110 !
b110 *
1$
#90000
0$
b111 &
b111 )
b1100 "
b1100 '
